saigon/__init__.py
saigon/static/js/saigon-md-requirements.js
saigon/static/ng/saigon.filters.js
saigon/static/ng/saigon.forms.js
saigon/static/ng/saigon.js
saigon/static/ng/saigon.urls.js
saigon/static/scss/saigon.scss
saigon/static/scss/saigon/_modules.scss
saigon/static/scss/saigon/_patterns.scss
saigon/static/scss/saigon/modules/_breakpoints.scss
saigon/static/scss/saigon/modules/_colors.scss
saigon/static/scss/saigon/modules/_gradients.scss
saigon/static/scss/saigon/modules/_grid.scss
saigon/static/scss/saigon/modules/_layout.scss
saigon/static/scss/saigon/modules/_shadows.scss
saigon/static/scss/saigon/modules/_utils.scss
saigon/static/scss/saigon/modules/_variables.scss
saigon/static/scss/saigon/patterns/_buttons.scss
saigon/static/scss/saigon/patterns/_colors-extra.scss
saigon/static/scss/saigon/patterns/_colors.scss
saigon/static/scss/saigon/patterns/_grid.scss
saigon/static/scss/saigon/patterns/_lists.scss
saigon/static/scss/saigon/patterns/_margins.scss
saigon/static/scss/saigon/patterns/_normalize.scss
saigon/static/scss/saigon/patterns/_paddings.scss
saigon/static/scss/saigon/patterns/_shadows.scss
saigon/static/scss/saigon/patterns/_tables.scss
saigon/static/scss/saigon/patterns/_utils.scss
saigon/templatetags/__init__.py
saigon/templatetags/ng_forms.py
saigon-1.0.4.dist-info/DESCRIPTION.rst
saigon-1.0.4.dist-info/METADATA
saigon-1.0.4.dist-info/RECORD
saigon-1.0.4.dist-info/WHEEL
saigon-1.0.4.dist-info/metadata.json
saigon-1.0.4.dist-info/top_level.txt
